{"ref":"db1c96cb-f5a9-4bc7-b68a-43eaeea873b1","content":"{\"version\":5,\"machineId\":\"038831a9-44f6-4d3f-82d7-ac7694ed18fb\",\"content\":\"[{\\\"identifier\\\":{\\\"id\\\":\\\"vscode.bat\\\"},\\\"preRelease\\\":false,\\\"version\\\":\\\"1.0.0\\\"},{\\\"identifier\\\":{\\\"id\\\":\\\"vscode.clojure\\\"},\\\"preRelease\\\":false,\\\"version\\\":\\\"1.0.0\\\"},{\\\"identifier\\\":{\\\"id\\\":\\\"vscode.coffeescript\\\"},\\\"preRelease\\\":false,\\\"version\\\":\\\"1.0.0\\\"},{\\\"identifier\\\":{\\\"id\\\":\\\"vscode.configuration-editing\\\"},\\\"preRelease\\\":false,\\\"version\\\":\\\"1.0.0\\\"},{\\\"identifier\\\":{\\\"id\\\":\\\"vscode.cpp\\\"},\\\"preRelease\\\":false,\\\"version\\\":\\\"1.0.0\\\"},{\\\"identifier\\\":{\\\"id\\\":\\\"vscode.csharp\\\"},\\\"preRelease\\\":false,\\\"version\\\":\\\"1.0.0\\\"},{\\\"identifier\\\":{\\\"id\\\":\\\"vscode.css\\\"},\\\"preRelease\\\":false,\\\"version\\\":\\\"1.0.0\\\"},{\\\"identifier\\\":{\\\"id\\\":\\\"vscode.css-language-features\\\"},\\\"preRelease\\\":false,\\\"version\\\":\\\"1.0.0\\\"},{\\\"identifier\\\":{\\\"id\\\":\\\"vscode.dart\\\"},\\\"preRelease\\\":false,\\\"version\\\":\\\"1.0.0\\\"},{\\\"identifier\\\":{\\\"id\\\":\\\"vscode.debug-auto-launch\\\"},\\\"preRelease\\\":false,\\\"version\\\":\\\"1.0.0\\\"},{\\\"identifier\\\":{\\\"id\\\":\\\"vscode.debug-server-ready\\\"},\\\"preRelease\\\":false,\\\"version\\\":\\\"1.0.0\\\"},{\\\"identifier\\\":{\\\"id\\\":\\\"vscode.docker\\\"},\\\"preRelease\\\":false,\\\"version\\\":\\\"1.0.0\\\"},{\\\"identifier\\\":{\\\"id\\\":\\\"vscode.emmet\\\"},\\\"preRelease\\\":false,\\\"version\\\":\\\"1.0.0\\\"},{\\\"identifier\\\":{\\\"id\\\":\\\"vscode.extension-editing\\\"},\\\"preRelease\\\":false,\\\"version\\\":\\\"1.0.0\\\"},{\\\"identifier\\\":{\\\"id\\\":\\\"vscode.fsharp\\\"},\\\"preRelease\\\":false,\\\"version\\\":\\\"1.0.0\\\"},{\\\"identifier\\\":{\\\"id\\\":\\\"vscode.git\\\"},\\\"preRelease\\\":false,\\\"version\\\":\\\"1.0.0\\\"},{\\\"identifier\\\":{\\\"id\\\":\\\"vscode.github\\\"},\\\"preRelease\\\":false,\\\"version\\\":\\\"0.0.1\\\"},{\\\"identifier\\\":{\\\"id\\\":\\\"vscode.github-authentication\\\"},\\\"preRelease\\\":false,\\\"version\\\":\\\"0.0.2\\\"},{\\\"identifier\\\":{\\\"id\\\":\\\"vscode.go\\\"},\\\"preRelease\\\":false,\\\"version\\\":\\\"1.0.0\\\"},{\\\"identifier\\\":{\\\"id\\\":\\\"vscode.groovy\\\"},\\\"preRelease\\\":false,\\\"version\\\":\\\"1.0.0\\\"},{\\\"identifier\\\":{\\\"id\\\":\\\"vscode.grunt\\\"},\\\"preRelease\\\":false,\\\"version\\\":\\\"1.0.0\\\"},{\\\"identifier\\\":{\\\"id\\\":\\\"vscode.gulp\\\"},\\\"preRelease\\\":false,\\\"version\\\":\\\"1.0.0\\\"},{\\\"identifier\\\":{\\\"id\\\":\\\"vscode.handlebars\\\"},\\\"preRelease\\\":false,\\\"version\\\":\\\"1.0.0\\\"},{\\\"identifier\\\":{\\\"id\\\":\\\"vscode.hlsl\\\"},\\\"preRelease\\\":false,\\\"version\\\":\\\"1.0.0\\\"},{\\\"identifier\\\":{\\\"id\\\":\\\"vscode.html\\\"},\\\"preRelease\\\":false,\\\"version\\\":\\\"1.0.0\\\"},{\\\"identifier\\\":{\\\"id\\\":\\\"vscode.html-language-features\\\"},\\\"preRelease\\\":false,\\\"version\\\":\\\"1.0.0\\\"},{\\\"identifier\\\":{\\\"id\\\":\\\"vscode.image-preview\\\"},\\\"preRelease\\\":false,\\\"version\\\":\\\"1.0.0\\\"},{\\\"identifier\\\":{\\\"id\\\":\\\"vscode.ini\\\"},\\\"preRelease\\\":false,\\\"version\\\":\\\"1.0.0\\\"},{\\\"identifier\\\":{\\\"id\\\":\\\"vscode.ipynb\\\"},\\\"preRelease\\\":false,\\\"version\\\":\\\"1.0.0\\\"},{\\\"identifier\\\":{\\\"id\\\":\\\"vscode.jake\\\"},\\\"preRelease\\\":false,\\\"version\\\":\\\"1.0.0\\\"},{\\\"identifier\\\":{\\\"id\\\":\\\"vscode.java\\\"},\\\"preRelease\\\":false,\\\"version\\\":\\\"1.0.0\\\"},{\\\"identifier\\\":{\\\"id\\\":\\\"vscode.javascript\\\"},\\\"preRelease\\\":false,\\\"version\\\":\\\"1.0.0\\\"},{\\\"identifier\\\":{\\\"id\\\":\\\"vscode.json\\\"},\\\"preRelease\\\":false,\\\"version\\\":\\\"1.0.0\\\"},{\\\"identifier\\\":{\\\"id\\\":\\\"vscode.json-language-features\\\"},\\\"preRelease\\\":false,\\\"version\\\":\\\"1.0.0\\\"},{\\\"identifier\\\":{\\\"id\\\":\\\"vscode.julia\\\"},\\\"preRelease\\\":false,\\\"version\\\":\\\"1.0.0\\\"},{\\\"identifier\\\":{\\\"id\\\":\\\"vscode.less\\\"},\\\"preRelease\\\":false,\\\"version\\\":\\\"1.0.0\\\"},{\\\"identifier\\\":{\\\"id\\\":\\\"vscode.log\\\"},\\\"preRelease\\\":false,\\\"version\\\":\\\"1.0.0\\\"},{\\\"identifier\\\":{\\\"id\\\":\\\"vscode.lua\\\"},\\\"preRelease\\\":false,\\\"version\\\":\\\"1.0.0\\\"},{\\\"identifier\\\":{\\\"id\\\":\\\"vscode.make\\\"},\\\"preRelease\\\":false,\\\"version\\\":\\\"1.0.0\\\"},{\\\"identifier\\\":{\\\"id\\\":\\\"vscode.markdown\\\"},\\\"preRelease\\\":false,\\\"version\\\":\\\"1.0.0\\\"},{\\\"identifier\\\":{\\\"id\\\":\\\"vscode.markdown-language-features\\\"},\\\"preRelease\\\":false,\\\"version\\\":\\\"1.0.0\\\"},{\\\"identifier\\\":{\\\"id\\\":\\\"vscode.markdown-math\\\"},\\\"preRelease\\\":false,\\\"version\\\":\\\"1.0.0\\\"},{\\\"identifier\\\":{\\\"id\\\":\\\"vscode.merge-conflict\\\"},\\\"preRelease\\\":false,\\\"version\\\":\\\"1.0.0\\\"},{\\\"identifier\\\":{\\\"id\\\":\\\"vscode.microsoft-authentication\\\"},\\\"preRelease\\\":false,\\\"version\\\":\\\"0.0.1\\\"},{\\\"identifier\\\":{\\\"id\\\":\\\"ms-vscode-remote.remote-wsl-recommender\\\",\\\"uuid\\\":\\\"cb296d3c-017a-4dee-83af-ebb5a5a16e9a\\\"},\\\"preRelease\\\":false,\\\"version\\\":\\\"0.0.12\\\"},{\\\"identifier\\\":{\\\"id\\\":\\\"ms-vscode.js-debug\\\",\\\"uuid\\\":\\\"25629058-ddac-4e17-abba-74678e126c5d\\\"},\\\"preRelease\\\":false,\\\"version\\\":\\\"1.62.0\\\"},{\\\"identifier\\\":{\\\"id\\\":\\\"ms-vscode.js-debug-companion\\\",\\\"uuid\\\":\\\"99cb0b7f-7354-4278-b8da-6cc79972169d\\\"},\\\"preRelease\\\":false,\\\"version\\\":\\\"1.0.15\\\"},{\\\"identifier\\\":{\\\"id\\\":\\\"ms-vscode.references-view\\\",\\\"uuid\\\":\\\"dc489f46-520d-4556-ae85-1f9eab3c412d\\\"},\\\"preRelease\\\":false,\\\"version\\\":\\\"0.0.81\\\"},{\\\"identifier\\\":{\\\"id\\\":\\\"ms-vscode.vscode-js-profile-table\\\",\\\"uuid\\\":\\\"7e52b41b-71ad-457b-ab7e-0620f1fc4feb\\\"},\\\"preRelease\\\":false,\\\"version\\\":\\\"0.0.18\\\"},{\\\"identifier\\\":{\\\"id\\\":\\\"vscode.npm\\\"},\\\"preRelease\\\":false,\\\"version\\\":\\\"1.0.1\\\"},{\\\"identifier\\\":{\\\"id\\\":\\\"vscode.objective-c\\\"},\\\"preRelease\\\":false,\\\"version\\\":\\\"1.0.0\\\"},{\\\"identifier\\\":{\\\"id\\\":\\\"vscode.perl\\\"},\\\"preRelease\\\":false,\\\"version\\\":\\\"1.0.0\\\"},{\\\"identifier\\\":{\\\"id\\\":\\\"vscode.php\\\"},\\\"preRelease\\\":false,\\\"version\\\":\\\"1.0.0\\\"},{\\\"identifier\\\":{\\\"id\\\":\\\"vscode.php-language-features\\\"},\\\"preRelease\\\":false,\\\"version\\\":\\\"1.0.0\\\"},{\\\"identifier\\\":{\\\"id\\\":\\\"vscode.powershell\\\"},\\\"preRelease\\\":false,\\\"version\\\":\\\"1.0.0\\\"},{\\\"identifier\\\":{\\\"id\\\":\\\"vscode.pug\\\"},\\\"preRelease\\\":false,\\\"version\\\":\\\"1.0.0\\\"},{\\\"identifier\\\":{\\\"id\\\":\\\"vscode.python\\\"},\\\"preRelease\\\":false,\\\"version\\\":\\\"1.0.0\\\"},{\\\"identifier\\\":{\\\"id\\\":\\\"vscode.r\\\"},\\\"preRelease\\\":false,\\\"version\\\":\\\"1.0.0\\\"},{\\\"identifier\\\":{\\\"id\\\":\\\"vscode.razor\\\"},\\\"preRelease\\\":false,\\\"version\\\":\\\"1.0.0\\\"},{\\\"identifier\\\":{\\\"id\\\":\\\"vscode.ruby\\\"},\\\"preRelease\\\":false,\\\"version\\\":\\\"1.0.0\\\"},{\\\"identifier\\\":{\\\"id\\\":\\\"vscode.rust\\\"},\\\"preRelease\\\":false,\\\"version\\\":\\\"1.0.0\\\"},{\\\"identifier\\\":{\\\"id\\\":\\\"vscode.scss\\\"},\\\"preRelease\\\":false,\\\"version\\\":\\\"1.0.0\\\"},{\\\"identifier\\\":{\\\"id\\\":\\\"vscode.search-result\\\"},\\\"preRelease\\\":false,\\\"version\\\":\\\"1.0.0\\\"},{\\\"identifier\\\":{\\\"id\\\":\\\"vscode.shaderlab\\\"},\\\"preRelease\\\":false,\\\"version\\\":\\\"1.0.0\\\"},{\\\"identifier\\\":{\\\"id\\\":\\\"vscode.shellscript\\\"},\\\"preRelease\\\":false,\\\"version\\\":\\\"1.0.0\\\"},{\\\"identifier\\\":{\\\"id\\\":\\\"vscode.simple-browser\\\"},\\\"preRelease\\\":false,\\\"version\\\":\\\"1.0.0\\\"},{\\\"identifier\\\":{\\\"id\\\":\\\"vscode.sql\\\"},\\\"preRelease\\\":false,\\\"version\\\":\\\"1.0.0\\\"},{\\\"identifier\\\":{\\\"id\\\":\\\"vscode.swift\\\"},\\\"preRelease\\\":false,\\\"version\\\":\\\"1.0.0\\\"},{\\\"identifier\\\":{\\\"id\\\":\\\"vscode.theme-abyss\\\"},\\\"preRelease\\\":false,\\\"version\\\":\\\"1.0.0\\\"},{\\\"identifier\\\":{\\\"id\\\":\\\"vscode.theme-defaults\\\"},\\\"preRelease\\\":false,\\\"version\\\":\\\"1.0.0\\\"},{\\\"identifier\\\":{\\\"id\\\":\\\"vscode.theme-kimbie-dark\\\"},\\\"preRelease\\\":false,\\\"version\\\":\\\"1.0.0\\\"},{\\\"identifier\\\":{\\\"id\\\":\\\"vscode.theme-monokai\\\"},\\\"preRelease\\\":false,\\\"version\\\":\\\"1.0.0\\\"},{\\\"identifier\\\":{\\\"id\\\":\\\"vscode.theme-monokai-dimmed\\\"},\\\"preRelease\\\":false,\\\"version\\\":\\\"1.0.0\\\"},{\\\"identifier\\\":{\\\"id\\\":\\\"vscode.theme-quietlight\\\"},\\\"preRelease\\\":false,\\\"version\\\":\\\"1.0.0\\\"},{\\\"identifier\\\":{\\\"id\\\":\\\"vscode.theme-red\\\"},\\\"preRelease\\\":false,\\\"version\\\":\\\"1.0.0\\\"},{\\\"identifier\\\":{\\\"id\\\":\\\"vscode.vscode-theme-seti\\\"},\\\"preRelease\\\":false,\\\"version\\\":\\\"1.0.0\\\"},{\\\"identifier\\\":{\\\"id\\\":\\\"vscode.theme-solarized-dark\\\"},\\\"preRelease\\\":false,\\\"version\\\":\\\"1.0.0\\\"},{\\\"identifier\\\":{\\\"id\\\":\\\"vscode.theme-solarized-light\\\"},\\\"preRelease\\\":false,\\\"version\\\":\\\"1.0.0\\\"},{\\\"identifier\\\":{\\\"id\\\":\\\"vscode.theme-tomorrow-night-blue\\\"},\\\"preRelease\\\":false,\\\"version\\\":\\\"1.0.0\\\"},{\\\"identifier\\\":{\\\"id\\\":\\\"vscode.typescript\\\"},\\\"preRelease\\\":false,\\\"version\\\":\\\"1.0.0\\\"},{\\\"identifier\\\":{\\\"id\\\":\\\"vscode.typescript-language-features\\\"},\\\"preRelease\\\":false,\\\"version\\\":\\\"1.0.0\\\"},{\\\"identifier\\\":{\\\"id\\\":\\\"vscode.vb\\\"},\\\"preRelease\\\":false,\\\"version\\\":\\\"1.0.0\\\"},{\\\"identifier\\\":{\\\"id\\\":\\\"vscode.xml\\\"},\\\"preRelease\\\":false,\\\"version\\\":\\\"1.0.0\\\"},{\\\"identifier\\\":{\\\"id\\\":\\\"vscode.yaml\\\"},\\\"preRelease\\\":false,\\\"version\\\":\\\"1.0.0\\\"},{\\\"identifier\\\":{\\\"id\\\":\\\"esbenp.prettier-vscode\\\",\\\"uuid\\\":\\\"96fa4707-6983-4489-b7c5-d5ffdfdcce90\\\"},\\\"preRelease\\\":false,\\\"version\\\":\\\"9.5.0\\\",\\\"installed\\\":true},{\\\"identifier\\\":{\\\"id\\\":\\\"ms-python.python\\\",\\\"uuid\\\":\\\"f1f59ae4-9318-4f3c-a9b5-81b2eaa5f8a5\\\"},\\\"preRelease\\\":false,\\\"version\\\":\\\"2022.6.0\\\",\\\"installed\\\":true},{\\\"identifier\\\":{\\\"id\\\":\\\"pkief.material-icon-theme\\\",\\\"uuid\\\":\\\"5db78037-f674-459f-a236-db622c427c5b\\\"},\\\"preRelease\\\":false,\\\"version\\\":\\\"4.18.1\\\",\\\"installed\\\":true,\\\"state\\\":{\\\"material-icon-theme.version\\\":\\\"4.18.1\\\"}},{\\\"identifier\\\":{\\\"id\\\":\\\"ritwickdey.liveserver\\\",\\\"uuid\\\":\\\"b63c44fd-0457-4696-99e9-dbfdf70d77de\\\"},\\\"preRelease\\\":false,\\\"version\\\":\\\"5.7.5\\\",\\\"installed\\\":true,\\\"state\\\":{\\\"liveServer.setup.version\\\":\\\"5.7.5\\\"}},{\\\"identifier\\\":{\\\"id\\\":\\\"syler.sass-indented\\\",\\\"uuid\\\":\\\"466468c3-1861-4ad1-bf3e-f9ad46545ebb\\\"},\\\"preRelease\\\":false,\\\"version\\\":\\\"1.8.19\\\",\\\"installed\\\":true},{\\\"identifier\\\":{\\\"id\\\":\\\"whatwedo.twig\\\",\\\"uuid\\\":\\\"3324c5be-43aa-4c39-a0f8-d94c2978804f\\\"},\\\"preRelease\\\":false,\\\"version\\\":\\\"1.0.2\\\",\\\"installed\\\":true},{\\\"identifier\\\":{\\\"id\\\":\\\"eamodio.gitlens\\\",\\\"uuid\\\":\\\"4de763bd-505d-4978-9575-2b7696ecf94e\\\"},\\\"preRelease\\\":false,\\\"version\\\":\\\"12.1.1\\\",\\\"installed\\\":true,\\\"state\\\":{\\\"gitlens:views:welcome:visible\\\":false,\\\"gitlens:synced:version\\\":\\\"12.1.1\\\"}},{\\\"identifier\\\":{\\\"id\\\":\\\"syler.ignore\\\",\\\"uuid\\\":\\\"4e051fca-a938-4e77-9732-a792d93a8169\\\"},\\\"preRelease\\\":false,\\\"version\\\":\\\"0.0.4\\\",\\\"installed\\\":true},{\\\"identifier\\\":{\\\"id\\\":\\\"redhat.java\\\",\\\"uuid\\\":\\\"198a707e-28af-4e84-8610-6e2f628dd12d\\\"},\\\"preRelease\\\":false,\\\"version\\\":\\\"1.6.0\\\",\\\"installed\\\":true},{\\\"identifier\\\":{\\\"id\\\":\\\"visualstudioexptteam.vscodeintellicode\\\",\\\"uuid\\\":\\\"876e8f93-74d0-4f4f-91b7-34a09f19f444\\\"},\\\"preRelease\\\":false,\\\"version\\\":\\\"1.2.20\\\",\\\"installed\\\":true},{\\\"identifier\\\":{\\\"id\\\":\\\"vscjava.vscode-java-debug\\\",\\\"uuid\\\":\\\"61fcd0cf-64d7-4836-8d6b-d55f4fb83281\\\"},\\\"preRelease\\\":false,\\\"version\\\":\\\"0.40.1\\\",\\\"installed\\\":true},{\\\"identifier\\\":{\\\"id\\\":\\\"vscjava.vscode-java-pack\\\",\\\"uuid\\\":\\\"96f11e1f-1a46-4592-b084-f025b2c2a81f\\\"},\\\"preRelease\\\":false,\\\"version\\\":\\\"0.22.4\\\",\\\"installed\\\":true,\\\"state\\\":{}},{\\\"identifier\\\":{\\\"id\\\":\\\"vscjava.vscode-maven\\\",\\\"uuid\\\":\\\"b0f06c6b-24fb-4d7b-bd79-bc5e2fa17312\\\"},\\\"preRelease\\\":false,\\\"version\\\":\\\"0.35.1\\\",\\\"installed\\\":true},{\\\"identifier\\\":{\\\"id\\\":\\\"mechatroner.rainbow-csv\\\",\\\"uuid\\\":\\\"3792588c-3d35-442d-91ea-fe6a755e8155\\\"},\\\"preRelease\\\":false,\\\"version\\\":\\\"2.3.0\\\",\\\"installed\\\":true},{\\\"identifier\\\":{\\\"id\\\":\\\"gabrielbb.vscode-lombok\\\",\\\"uuid\\\":\\\"4b3ff6b3-747b-48b1-9593-61195ead981b\\\"},\\\"preRelease\\\":false,\\\"version\\\":\\\"1.0.1\\\",\\\"installed\\\":true},{\\\"identifier\\\":{\\\"id\\\":\\\"natqe.reload\\\",\\\"uuid\\\":\\\"b9484b93-0531-4fd3-b3dd-9ff58dcfe678\\\"},\\\"preRelease\\\":false,\\\"version\\\":\\\"0.0.6\\\",\\\"installed\\\":true},{\\\"identifier\\\":{\\\"id\\\":\\\"pivotal.vscode-spring-boot\\\",\\\"uuid\\\":\\\"0efda145-8595-4ff7-98ef-1e3abc5e5757\\\"},\\\"preRelease\\\":false,\\\"version\\\":\\\"1.33.0\\\",\\\"installed\\\":true},{\\\"identifier\\\":{\\\"id\\\":\\\"vscjava.vscode-spring-boot-dashboard\\\",\\\"uuid\\\":\\\"27fc0e8e-1341-4f52-9219-4e0f81590937\\\"},\\\"preRelease\\\":false,\\\"version\\\":\\\"0.3.1\\\",\\\"installed\\\":true},{\\\"identifier\\\":{\\\"id\\\":\\\"angular.ng-template\\\",\\\"uuid\\\":\\\"a92d457e-6f3f-4167-8087-1a54e1b6e00e\\\"},\\\"preRelease\\\":false,\\\"version\\\":\\\"13.3.2\\\",\\\"installed\\\":true},{\\\"identifier\\\":{\\\"id\\\":\\\"ritwickdey.live-sass\\\",\\\"uuid\\\":\\\"ad94b437-b5a7-4249-bf5f-df472ae0d084\\\"},\\\"preRelease\\\":false,\\\"version\\\":\\\"3.0.0\\\",\\\"installed\\\":true},{\\\"identifier\\\":{\\\"id\\\":\\\"mhutchie.git-graph\\\",\\\"uuid\\\":\\\"438221f8-1107-4ccd-a6fe-f3b7fe0856b7\\\"},\\\"preRelease\\\":false,\\\"version\\\":\\\"1.30.0\\\",\\\"installed\\\":true},{\\\"identifier\\\":{\\\"id\\\":\\\"apollographql.vscode-apollo\\\",\\\"uuid\\\":\\\"de44183f-5377-4ceb-ac15-79364a30070c\\\"},\\\"preRelease\\\":false,\\\"version\\\":\\\"1.19.11\\\",\\\"installed\\\":true},{\\\"identifier\\\":{\\\"id\\\":\\\"prisma.prisma\\\",\\\"uuid\\\":\\\"33ce9d6b-41cf-4972-a62b-386f7201981d\\\"},\\\"preRelease\\\":false,\\\"version\\\":\\\"3.13.0\\\",\\\"installed\\\":true},{\\\"identifier\\\":{\\\"id\\\":\\\"eg2.vscode-npm-script\\\",\\\"uuid\\\":\\\"ae9e3eb0-3357-4cc0-90ee-598d2d384757\\\"},\\\"preRelease\\\":false,\\\"version\\\":\\\"0.3.25\\\",\\\"installed\\\":true},{\\\"identifier\\\":{\\\"id\\\":\\\"christian-kohler.npm-intellisense\\\",\\\"uuid\\\":\\\"dff6b801-247e-40e9-82e8-8c9b1d19d1b8\\\"},\\\"preRelease\\\":false,\\\"version\\\":\\\"1.4.1\\\",\\\"installed\\\":true},{\\\"identifier\\\":{\\\"id\\\":\\\"geeksharp.openssl-configuration-file\\\",\\\"uuid\\\":\\\"4dbb8f55-285c-451e-9340-3642fbab3603\\\"},\\\"preRelease\\\":false,\\\"version\\\":\\\"0.0.1\\\",\\\"installed\\\":true},{\\\"identifier\\\":{\\\"id\\\":\\\"ms-python.vscode-pylance\\\",\\\"uuid\\\":\\\"364d2426-116a-433a-a5d8-a5098dc3afbd\\\"},\\\"preRelease\\\":false,\\\"version\\\":\\\"2022.4.3\\\",\\\"installed\\\":true},{\\\"identifier\\\":{\\\"id\\\":\\\"hashicorp.terraform\\\",\\\"uuid\\\":\\\"4a23294b-fd16-4c51-9759-da9936474cf8\\\"},\\\"preRelease\\\":false,\\\"version\\\":\\\"2.17.0\\\",\\\"installed\\\":true},{\\\"identifier\\\":{\\\"id\\\":\\\"4ops.terraform\\\",\\\"uuid\\\":\\\"b861aa84-146f-440f-b6be-76124b02b729\\\"},\\\"preRelease\\\":false,\\\"version\\\":\\\"0.2.2\\\",\\\"installed\\\":true},{\\\"identifier\\\":{\\\"id\\\":\\\"vscode.diff\\\"},\\\"preRelease\\\":false,\\\"version\\\":\\\"1.0.0\\\"},{\\\"identifier\\\":{\\\"id\\\":\\\"vscode.git-base\\\"},\\\"preRelease\\\":false,\\\"version\\\":\\\"1.0.0\\\"},{\\\"identifier\\\":{\\\"id\\\":\\\"justusadam.language-haskell\\\",\\\"uuid\\\":\\\"270c1d3b-a657-446f-83b8-ab32fd7af006\\\"},\\\"preRelease\\\":false,\\\"version\\\":\\\"3.4.0\\\",\\\"installed\\\":true},{\\\"identifier\\\":{\\\"id\\\":\\\"redhat.vscode-yaml\\\",\\\"uuid\\\":\\\"2061917f-f76a-458a-8da9-f162de22b97e\\\"},\\\"preRelease\\\":false,\\\"version\\\":\\\"1.2.2\\\",\\\"installed\\\":true},{\\\"identifier\\\":{\\\"id\\\":\\\"tomoki1207.pdf\\\",\\\"uuid\\\":\\\"4386e6f6-ec10-4463-9d23-c24278718947\\\"},\\\"preRelease\\\":false,\\\"version\\\":\\\"1.2.0\\\",\\\"installed\\\":true},{\\\"identifier\\\":{\\\"id\\\":\\\"redhat.vscode-xml\\\",\\\"uuid\\\":\\\"6703768d-d42f-474e-9f6e-5f288d53f6e8\\\"},\\\"preRelease\\\":false,\\\"version\\\":\\\"0.18.2\\\",\\\"installed\\\":true},{\\\"identifier\\\":{\\\"id\\\":\\\"redhat.fabric8-analytics\\\",\\\"uuid\\\":\\\"efcb43ca-77e6-43e4-8ddc-ada617cb34bd\\\"},\\\"preRelease\\\":false,\\\"version\\\":\\\"0.3.5\\\",\\\"installed\\\":true},{\\\"identifier\\\":{\\\"id\\\":\\\"vscode.latex\\\"},\\\"preRelease\\\":false,\\\"version\\\":\\\"1.0.0\\\"},{\\\"identifier\\\":{\\\"id\\\":\\\"pivotal.vscode-boot-dev-pack\\\",\\\"uuid\\\":\\\"26069f6b-56ea-4c29-8e28-371698a60020\\\"},\\\"preRelease\\\":false,\\\"version\\\":\\\"0.1.0\\\",\\\"installed\\\":true},{\\\"identifier\\\":{\\\"id\\\":\\\"vscjava.vscode-spring-initializr\\\",\\\"uuid\\\":\\\"a205ad34-542b-4c67-a9ed-f645103ad9c0\\\"},\\\"preRelease\\\":false,\\\"version\\\":\\\"0.8.0\\\",\\\"installed\\\":true},{\\\"identifier\\\":{\\\"id\\\":\\\"robbowen.synthwave-vscode\\\",\\\"uuid\\\":\\\"e5fd2b56-1637-4d4f-8252-6c9d416f9a28\\\"},\\\"preRelease\\\":false,\\\"version\\\":\\\"0.1.11\\\",\\\"installed\\\":true},{\\\"identifier\\\":{\\\"id\\\":\\\"dbaeumer.vscode-eslint\\\",\\\"uuid\\\":\\\"583b2b34-2c1e-4634-8c0b-0b82e283ea3a\\\"},\\\"preRelease\\\":true,\\\"version\\\":\\\"2.2.3\\\",\\\"disabled\\\":true,\\\"installed\\\":true},{\\\"identifier\\\":{\\\"id\\\":\\\"ms-toolsai.jupyter\\\",\\\"uuid\\\":\\\"6c2f1801-1e7f-45b2-9b5c-7782f1e076e8\\\"},\\\"preRelease\\\":false,\\\"version\\\":\\\"2022.4.1011282140\\\",\\\"installed\\\":true},{\\\"identifier\\\":{\\\"id\\\":\\\"vscode.builtin-notebook-renderers\\\"},\\\"preRelease\\\":false,\\\"version\\\":\\\"1.0.0\\\"},{\\\"identifier\\\":{\\\"id\\\":\\\"vscode.restructuredtext\\\"},\\\"preRelease\\\":false,\\\"version\\\":\\\"1.0.0\\\"},{\\\"identifier\\\":{\\\"id\\\":\\\"adpyke.vscode-sql-formatter\\\",\\\"uuid\\\":\\\"ac70a31d-d9ab-417b-b259-baf7cd9d6cb0\\\"},\\\"preRelease\\\":false,\\\"version\\\":\\\"1.4.4\\\",\\\"installed\\\":true},{\\\"identifier\\\":{\\\"id\\\":\\\"ms-mssql.data-workspace-vscode\\\",\\\"uuid\\\":\\\"88e082b7-d289-4c59-bde4-4c61e0280428\\\"},\\\"preRelease\\\":false,\\\"version\\\":\\\"0.1.1\\\",\\\"installed\\\":true},{\\\"identifier\\\":{\\\"id\\\":\\\"ms-mssql.mssql\\\",\\\"uuid\\\":\\\"4bf45e86-a448-4531-8c01-ef33f4536306\\\"},\\\"preRelease\\\":false,\\\"version\\\":\\\"1.13.0\\\",\\\"installed\\\":true},{\\\"identifier\\\":{\\\"id\\\":\\\"ms-mssql.sql-database-projects-vscode\\\",\\\"uuid\\\":\\\"4e9e1d12-64b6-4573-9203-f601d27de5a3\\\"},\\\"preRelease\\\":false,\\\"version\\\":\\\"0.14.1\\\",\\\"installed\\\":true},{\\\"identifier\\\":{\\\"id\\\":\\\"ms-mssql.sql-bindings-vscode\\\",\\\"uuid\\\":\\\"48154c8d-77c4-4978-a3a2-807fc5266321\\\"},\\\"preRelease\\\":false,\\\"version\\\":\\\"0.0.1\\\",\\\"installed\\\":true},{\\\"identifier\\\":{\\\"id\\\":\\\"xdebug.php-debug\\\",\\\"uuid\\\":\\\"044b4b31-2969-4af3-895d-855433b8b46d\\\"},\\\"preRelease\\\":false,\\\"version\\\":\\\"1.26.1\\\",\\\"installed\\\":true},{\\\"identifier\\\":{\\\"id\\\":\\\"ms-azuretools.vscode-docker\\\",\\\"uuid\\\":\\\"0479fc1c-3d67-49f9-b087-fb9069afe48f\\\"},\\\"preRelease\\\":false,\\\"version\\\":\\\"1.22.0\\\",\\\"installed\\\":true},{\\\"identifier\\\":{\\\"id\\\":\\\"xdebug.php-pack\\\",\\\"uuid\\\":\\\"1a9300c9-36a6-44d1-9d09-ada3641b8727\\\"},\\\"preRelease\\\":false,\\\"version\\\":\\\"1.0.3\\\",\\\"installed\\\":true},{\\\"identifier\\\":{\\\"id\\\":\\\"zobo.php-intellisense\\\",\\\"uuid\\\":\\\"3eddb68d-a5dd-43fb-be03-6f508d98fe97\\\"},\\\"preRelease\\\":false,\\\"version\\\":\\\"1.0.6\\\",\\\"installed\\\":true},{\\\"identifier\\\":{\\\"id\\\":\\\"wallabyjs.quokka-vscode\\\",\\\"uuid\\\":\\\"aae0701b-111f-49c1-9000-abd37a442f28\\\"},\\\"preRelease\\\":false,\\\"version\\\":\\\"1.0.477\\\",\\\"installed\\\":true,\\\"state\\\":{\\\"quokka.syncSettings\\\":[{\\\"fileName\\\":\\\"~/.quokka/.vscode.settings\\\",\\\"content\\\":\\\"1654421816033\\\"},{\\\"fileName\\\":\\\"~/.quokka/.qid\\\",\\\"content\\\":\\\"957aa211-c42e-4deb-a2a5-5d6cfdb27ec0\\\"},{\\\"fileName\\\":\\\"~/.quokka/.qlc\\\"},{\\\"fileName\\\":\\\"~/.quokka/config.json\\\",\\\"content\\\":\\\"{\\\\\\\"pro\\\\\\\":false}\\\"},{\\\"fileName\\\":\\\"~/.quokka/notifications.json\\\",\\\"content\\\":\\\"{\\\\\\\"suggestConfigAutoDetection_undefined\\\\\\\":{},\\\\\\\"debuggerEditContinueLimitationInCommunityEdition\\\\\\\":{}}\\\"},{\\\"fileName\\\":\\\"~/.quokka/startPage.json\\\",\\\"content\\\":\\\"{\\\\\\\"version\\\\\\\":5}\\\"},{\\\"fileName\\\":\\\"~/.quokka/user.data\\\"},{\\\"fileName\\\":\\\"~/.quokka/user.id\\\"},{\\\"fileName\\\":\\\"~/.wallaby/.ol\\\"}]}},{\\\"identifier\\\":{\\\"id\\\":\\\"golang.go\\\",\\\"uuid\\\":\\\"d6f6cfea-4b6f-41f4-b571-6ad2ab7918da\\\"},\\\"preRelease\\\":false,\\\"version\\\":\\\"0.33.0\\\",\\\"installed\\\":true},{\\\"identifier\\\":{\\\"id\\\":\\\"cschlosser.doxdocgen\\\",\\\"uuid\\\":\\\"da7e26d5-d57c-4742-ab47-d77fb189e195\\\"},\\\"preRelease\\\":false,\\\"version\\\":\\\"1.4.0\\\",\\\"installed\\\":true},{\\\"identifier\\\":{\\\"id\\\":\\\"jeff-hykin.better-cpp-syntax\\\",\\\"uuid\\\":\\\"73767f91-7dcb-43cb-90b3-596d073eea1f\\\"},\\\"preRelease\\\":false,\\\"version\\\":\\\"1.15.14\\\",\\\"installed\\\":true},{\\\"identifier\\\":{\\\"id\\\":\\\"ms-vscode.cmake-tools\\\",\\\"uuid\\\":\\\"7c889349-8749-43d4-8b5e-08939936d7f4\\\"},\\\"preRelease\\\":false,\\\"version\\\":\\\"1.10.5\\\",\\\"installed\\\":true},{\\\"identifier\\\":{\\\"id\\\":\\\"ms-vscode.cpptools\\\",\\\"uuid\\\":\\\"690b692e-e8a9-493f-b802-8089d50ac1b2\\\"},\\\"preRelease\\\":false,\\\"version\\\":\\\"1.9.8\\\",\\\"installed\\\":true},{\\\"identifier\\\":{\\\"id\\\":\\\"ms-vscode.cpptools-extension-pack\\\",\\\"uuid\\\":\\\"3957b2f6-f086-49b5-a7b4-5da772123130\\\"},\\\"preRelease\\\":false,\\\"version\\\":\\\"1.2.0\\\",\\\"installed\\\":true},{\\\"identifier\\\":{\\\"id\\\":\\\"ms-vscode.cpptools-themes\\\",\\\"uuid\\\":\\\"99b17261-8f6e-45f0-9ad5-a69c6f509a4f\\\"},\\\"preRelease\\\":false,\\\"version\\\":\\\"1.0.0\\\",\\\"installed\\\":true},{\\\"identifier\\\":{\\\"id\\\":\\\"twxs.cmake\\\",\\\"uuid\\\":\\\"2be7cf14-2603-402e-9771-fd79df83cdf8\\\"},\\\"preRelease\\\":false,\\\"version\\\":\\\"0.0.17\\\",\\\"installed\\\":true}]\"}","skippedExtensions":[]}